pi_security_cam/__init__.py
pi_security_cam/dropbox_uploader.py
pi_security_cam/logger.py
pi_security_cam/runtime.py
pi_security_cam/security_camera.py
pi_security_cam-0.1.0.dist-info/METADATA
pi_security_cam-0.1.0.dist-info/RECORD
pi_security_cam-0.1.0.dist-info/WHEEL
pi_security_cam-0.1.0.dist-info/top_level.txt
