Metadata-Version: 2.1
Name: pi-security-cam
Version: 0.1.0
Summary: Security camera built for Raspberry Pi
Home-page: http://github.com/tjkessler/pi-security-cam
Author: Travis Kessler
Author-email: travis.j.kessler@gmail.com
License: MIT
Platform: UNKNOWN
Requires-Dist: dropbox
Requires-Dist: opencv-python
